Metadata-Version: 2.1
Name: parseval
Version: 1.0.0
Summary: parseval is a data validation tool for python. It provides numerous API to parse and validate data for all native data-types. it handles data on atomic level and focuses on validation part primarily.
Home-page: https://parseval.readthedocs.io/en/latest/
Author: Saumalya Sarkar
Author-email: saumalya75@gmail.com
License: MIT
Download-URL: https://github.com/saumalya75/parseval/archive/v1.0.0.tar.gz
Keywords: python
Platform: UNKNOWN
Classifier: Development Status :: 5 - Production/Stable
Classifier: Intended Audience :: Developers
Classifier: Topic :: Software Development
Classifier: License :: OSI Approved :: MIT License
Classifier: Programming Language :: Python :: 3
Classifier: Programming Language :: Python :: 3.7
Classifier: Programming Language :: Python :: 3.8
